cortical_tools/__init__.py
cortical_tools/common.py
cortical_tools/files.py
cortical_tools/mesh.py
cortical_tools/mesh_vertex.py
cortical_tools/utils.py
cortical_tools/datasets/__init__.py
cortical_tools/datasets/microns_prod.py
cortical_tools/datasets/microns_public.py
cortical_tools/datasets/v1dd.py
cortical_tools/datasets/v1dd_public.py
cortical_tools-0.0.6.dist-info/METADATA
cortical_tools-0.0.6.dist-info/WHEEL
cortical_tools-0.0.6.dist-info/licenses/LICENSE
cortical_tools-0.0.6.dist-info/RECORD
