Metadata-Version: 2.4
Name: cortical-tools
Version: 0.0.6
Summary: Client for cortical CAVE datasets
Author-email: Casey Schneider-Mizell <caseysm@gmail.com>
License-File: LICENSE
Classifier: License :: OSI Approved :: MIT License
Requires-Python: >=3.10
Requires-Dist: caveclient>=7.7.4
Requires-Dist: cloud-volume>=12.3.1
Requires-Dist: gpytoolbox>=0.3.6
Requires-Dist: nglui>=4.4.2
Requires-Dist: numpy>=2.0.2
Requires-Dist: pandas>=2.2.3
Requires-Dist: pcg-skel>=1.3.1
Requires-Dist: standard-transform>=1.4.1
Requires-Dist: tqdm-joblib>=0.0.4
